{
  "france_power_exchanges": [
    {
      "start_date": "2025-10-10T00:00:00+02:00",
      "end_date": "2025-10-11T00:00:00+02:00",
      "updated_date": "2025-10-09T13:28:38+02:00",
      "values": [
        {
          "start_date": "2025-10-10T00:00:00+02:00",
          "end_date": "2025-10-10T01:00:00+02:00",
          "value": 11281.5,
          "price": 94.12
        },
        {
          "start_date": "2025-10-10T01:00:00+02:00",
          "end_date": "2025-10-10T02:00:00+02:00",
          "value": 11578.85,
          "price": 87.7
        },
        {
          "start_date": "2025-10-10T02:00:00+02:00",
          "end_date": "2025-10-10T03:00:00+02:00",
          "value": 11770,
          "price": 81.59
        },
        {
          "start_date": "2025-10-10T03:00:00+02:00",
          "end_date": "2025-10-10T04:00:00+02:00",
          "value": 12184.3,
          "price": 73.5
        },
        {
          "start_date": "2025-10-10T04:00:00+02:00",
          "end_date": "2025-10-10T05:00:00+02:00",
          "value": 12342.65,
          "price": 66
        },
        {
          "start_date": "2025-10-10T05:00:00+02:00",
          "end_date": "2025-10-10T06:00:00+02:00",
          "value": 11504.05,
          "price": 74.41
        },
        {
          "start_date": "2025-10-10T06:00:00+02:00",
          "end_date": "2025-10-10T07:00:00+02:00",
          "value": 11052.75,
          "price": 91.57
        },
        {
          "start_date": "2025-10-10T07:00:00+02:00",
          "end_date": "2025-10-10T08:00:00+02:00",
          "value": 12794.3,
          "price": 96.38
        },
        {
          "start_date": "2025-10-10T08:00:00+02:00",
          "end_date": "2025-10-10T09:00:00+02:00",
          "value": 12881.15,
          "price": 140.25
        },
        {
          "start_date": "2025-10-10T09:00:00+02:00",
          "end_date": "2025-10-10T10:00:00+02:00",
          "value": 14444.95,
          "price": 122.56
        },
        {
          "start_date": "2025-10-10T10:00:00+02:00",
          "end_date": "2025-10-10T11:00:00+02:00",
          "value": 14683.6,
          "price": 97.16
        },
        {
          "start_date": "2025-10-10T11:00:00+02:00",
          "end_date": "2025-10-10T12:00:00+02:00",
          "value": 15164.95,
          "price": 81.22
        },
        {
          "start_date": "2025-10-10T12:00:00+02:00",
          "end_date": "2025-10-10T13:00:00+02:00",
          "value": 16413.85,
          "price": 78.64
        },
        {
          "start_date": "2025-10-10T13:00:00+02:00",
          "end_date": "2025-10-10T14:00:00+02:00",
          "value": 16825.4,
          "price": 48.32
        },
        {
          "start_date": "2025-10-10T14:00:00+02:00",
          "end_date": "2025-10-10T15:00:00+02:00",
          "value": 17201.35,
          "price": 31.35
        },
        {
          "start_date": "2025-10-10T15:00:00+02:00",
          "end_date": "2025-10-10T16:00:00+02:00",
          "value": 16532.75,
          "price": 38.27
        },
        {
          "start_date": "2025-10-10T16:00:00+02:00",
          "end_date": "2025-10-10T17:00:00+02:00",
          "value": 15383.2,
          "price": 44.5
        },
        {
          "start_date": "2025-10-10T17:00:00+02:00",
          "end_date": "2025-10-10T18:00:00+02:00",
          "value": 13408.3,
          "price": 66.11
        },
        {
          "start_date": "2025-10-10T18:00:00+02:00",
          "end_date": "2025-10-10T19:00:00+02:00",
          "value": 13014.75,
          "price": 85.47
        },
        {
          "start_date": "2025-10-10T19:00:00+02:00",
          "end_date": "2025-10-10T20:00:00+02:00",
          "value": 13493.25,
          "price": 108.5
        },
        {
          "start_date": "2025-10-10T20:00:00+02:00",
          "end_date": "2025-10-10T21:00:00+02:00",
          "value": 14981,
          "price": 121.7
        },
        {
          "start_date": "2025-10-10T21:00:00+02:00",
          "end_date": "2025-10-10T22:00:00+02:00",
          "value": 14795.2,
          "price": 105.63
        },
        {
          "start_date": "2025-10-10T22:00:00+02:00",
          "end_date": "2025-10-10T23:00:00+02:00",
          "value": 14810.8,
          "price": 90.92
        },
        {
          "start_date": "2025-10-10T23:00:00+02:00",
          "end_date": "2025-10-11T00:00:00+02:00",
          "value": 13680.55,
          "price": 94.56
        }
      ]
    }
  ]
}