{
  "france_power_exchanges": [
    {
      "start_date": "2025-09-04T00:00:00+02:00",
      "end_date": "2025-09-05T00:00:00+02:00",
      "updated_date": "2025-09-03T13:19:27+02:00",
      "values": [
        {
          "start_date": "2025-09-04T00:00:00+02:00",
          "end_date": "2025-09-04T01:00:00+02:00",
          "value": 12014.7,
          "price": 19.84
        },
        {
          "start_date": "2025-09-04T01:00:00+02:00",
          "end_date": "2025-09-04T02:00:00+02:00",
          "value": 12293.8,
          "price": 14.81
        },
        {
          "start_date": "2025-09-04T02:00:00+02:00",
          "end_date": "2025-09-04T03:00:00+02:00",
          "value": 12968.5,
          "price": 14.3
        },
        {
          "start_date": "2025-09-04T03:00:00+02:00",
          "end_date": "2025-09-04T04:00:00+02:00",
          "value": 13902.8,
          "price": 5.96
        },
        {
          "start_date": "2025-09-04T04:00:00+02:00",
          "end_date": "2025-09-04T05:00:00+02:00",
          "value": 13651.6,
          "price": 5.99
        },
        {
          "start_date": "2025-09-04T05:00:00+02:00",
          "end_date": "2025-09-04T06:00:00+02:00",
          "value": 13205.8,
          "price": 11.49
        },
        {
          "start_date": "2025-09-04T06:00:00+02:00",
          "end_date": "2025-09-04T07:00:00+02:00",
          "value": 13306.2,
          "price": 42.15
        },
        {
          "start_date": "2025-09-04T07:00:00+02:00",
          "end_date": "2025-09-04T08:00:00+02:00",
          "value": 14055.2,
          "price": 52.04
        },
        {
          "start_date": "2025-09-04T08:00:00+02:00",
          "end_date": "2025-09-04T09:00:00+02:00",
          "value": 14552,
          "price": 55.89
        },
        {
          "start_date": "2025-09-04T09:00:00+02:00",
          "end_date": "2025-09-04T10:00:00+02:00",
          "value": 16165.6,
          "price": 49.6
        },
        {
          "start_date": "2025-09-04T10:00:00+02:00",
          "end_date": "2025-09-04T11:00:00+02:00",
          "value": 15322.9,
          "price": 18.07
        },
        {
          "start_date": "2025-09-04T11:00:00+02:00",
          "end_date": "2025-09-04T12:00:00+02:00",
          "value": 18036.9,
          "price": 5.79
        },
        {
          "start_date": "2025-09-04T12:00:00+02:00",
          "end_date": "2025-09-04T13:00:00+02:00",
          "value": 19292.5,
          "price": 3.2
        },
        {
          "start_date": "2025-09-04T13:00:00+02:00",
          "end_date": "2025-09-04T14:00:00+02:00",
          "value": 18562.3,
          "price": 1.72
        },
        {
          "start_date": "2025-09-04T14:00:00+02:00",
          "end_date": "2025-09-04T15:00:00+02:00",
          "value": 19469.2,
          "price": 1.6
        },
        {
          "start_date": "2025-09-04T15:00:00+02:00",
          "end_date": "2025-09-04T16:00:00+02:00",
          "value": 19188.2,
          "price": 1.55
        },
        {
          "start_date": "2025-09-04T16:00:00+02:00",
          "end_date": "2025-09-04T17:00:00+02:00",
          "value": 18515.6,
          "price": 3.7
        },
        {
          "start_date": "2025-09-04T17:00:00+02:00",
          "end_date": "2025-09-04T18:00:00+02:00",
          "value": 16590.9,
          "price": 7.01
        },
        {
          "start_date": "2025-09-04T18:00:00+02:00",
          "end_date": "2025-09-04T19:00:00+02:00",
          "value": 12776.2,
          "price": 28.19
        },
        {
          "start_date": "2025-09-04T19:00:00+02:00",
          "end_date": "2025-09-04T20:00:00+02:00",
          "value": 14155.4,
          "price": 62.19
        },
        {
          "start_date": "2025-09-04T20:00:00+02:00",
          "end_date": "2025-09-04T21:00:00+02:00",
          "value": 12958.3,
          "price": 102.5
        },
        {
          "start_date": "2025-09-04T21:00:00+02:00",
          "end_date": "2025-09-04T22:00:00+02:00",
          "value": 13502.7,
          "price": 80.74
        },
        {
          "start_date": "2025-09-04T22:00:00+02:00",
          "end_date": "2025-09-04T23:00:00+02:00",
          "value": 13166.7,
          "price": 84.8
        },
        {
          "start_date": "2025-09-04T23:00:00+02:00",
          "end_date": "2025-09-05T00:00:00+02:00",
          "value": 12351.2,
          "price": 62.18
        }
      ]
    }
  ]
}